reclist/__init__.py
reclist/charts.py
reclist/logs.py
reclist/metadata.py
reclist/reclist.py
reclist/similarity_models.py
reclist/metrics/__init__.py
reclist/metrics/distance_metrics.py
reclist/metrics/hits.py
reclist/metrics/perturbation.py
reclist/metrics/price_homogeneity.py
reclist/metrics/standard_metrics.py
reclist-2.1.0.dist-info/AUTHORS.rst
reclist-2.1.0.dist-info/LICENSE
reclist-2.1.0.dist-info/METADATA
reclist-2.1.0.dist-info/WHEEL
reclist-2.1.0.dist-info/top_level.txt
reclist-2.1.0.dist-info/RECORD
