Metadata-Version: 2.1
Name: reclist
Version: 2.1.0
Summary: RecList
Home-page: https://github.com/jacopotagliabue/reclist
Author: RecList
Author-email: 
License: MIT license
Keywords: reclist
Classifier: Development Status :: 2 - Pre-Alpha
Classifier: Intended Audience :: Developers
Classifier: License :: OSI Approved :: MIT License
Classifier: Natural Language :: English
Classifier: Programming Language :: Python :: 3
Classifier: Programming Language :: Python :: 3.6
Classifier: Programming Language :: Python :: 3.7
Classifier: Programming Language :: Python :: 3.8
Requires-Python: >=3.6
License-File: LICENSE
License-File: AUTHORS.rst
Requires-Dist: pandas (>=1.3.5)
Requires-Dist: gensim (==4.3.1)
Requires-Dist: appdirs (==1.4.4)
Requires-Dist: wget (==3.2)
Requires-Dist: requests (>=2.22.0)
Requires-Dist: tqdm (==4.65)
Requires-Dist: matplotlib (==3.6.3)
Requires-Dist: numpy (>=1.19.5)
Requires-Dist: pathos (==0.2.8)
Requires-Dist: networkx (==2.6.3)
Requires-Dist: python-Levenshtein (==0.12.2)
Requires-Dist: pyarrow (==12.0.1)
Requires-Dist: scikit-learn
Requires-Dist: rich
Provides-Extra: dev
Requires-Dist: black (==22.3.0) ; extra == 'dev'
Requires-Dist: isort (==5.10.1) ; extra == 'dev'
Requires-Dist: pre-commit (==2.20.0) ; extra == 'dev'
